mb_detect.py
mb_detect-1.0.4.dist-info/licenses/LICENSE.md
mb_detect-1.0.4.dist-info/METADATA
mb_detect-1.0.4.dist-info/WHEEL
mb_detect-1.0.4.dist-info/top_level.txt
mb_detect-1.0.4.dist-info/RECORD
