Metadata-Version: 2.4
Name: mb_detect
Version: 1.0.4
Summary: A smart serial port detector for BBC micro:bit
Home-page: https://github.com/mrgallen/mb_detect
Author: Eoin Gallen
Author-email: egallen@sainteunans.com
License: MIT
Classifier: Programming Language :: Python :: 3
Classifier: License :: OSI Approved :: MIT License
Classifier: Operating System :: OS Independent
License-File: LICENSE.md
Requires-Dist: pyserial
Dynamic: author
Dynamic: author-email
Dynamic: classifier
Dynamic: description
Dynamic: description-content-type
Dynamic: home-page
Dynamic: license
Dynamic: license-file
Dynamic: requires-dist
Dynamic: summary
